setup.py
keyholder/__init__.py
keyholder/etcd_handler.py
keyholder/keyHandler.py
keyholder/keyholder.py
keyholder/zoo_handler.py
keyholder.egg-info/PKG-INFO
keyholder.egg-info/SOURCES.txt
keyholder.egg-info/dependency_links.txt
keyholder.egg-info/not-zip-safe
keyholder.egg-info/requires.txt
keyholder.egg-info/top_level.txt