Metadata-Version: 1.0
Name: keyholder
Version: 0.3.3
Summary: Wrapper for multiple key-value stores
Home-page: https://github.com/s0urc3c0d3/keyholder
Author: Grzegorz Dwornicki
Author-email: gd1100@gmail.com
License: MIT
Platform: UNKNOWN
